{
    "batch_meta": {
        "export_time": "2026-06-04 11:11:00",
        "nx_version": "NX",
        "part_name": "DIE2-07-M260040-P2",
        "total_operations": 12,
        "batch_timestamp": "20260604_111100",
        "success_operations": 12,
        "fail_operations": 0
    },
    "operations": [
        {
            "operation_name": "A_ZXZ",
            "operation_type": "HoleDrilling",
            "total_params": 1,
            "parameters": [
                {
                    "id": 124,
                    "display_name": "Toolpath Time",
                    "type": "Double",
                    "value": 0.502728
                }
            ],
            "status": "success"
        },
        {
            "operation_name": "A_W1_A6",
            "operation_type": "HoleDrilling",
            "total_params": 1,
            "parameters": [
                {
                    "id": 124,
                    "display_name": "Toolpath Time",
                    "type": "Double",
                    "value": 1.04321
                }
            ],
            "status": "success"
        },
        {
            "operation_name": "A_C_A6.1",
            "operation_type": "HoleDrilling",
            "total_params": 1,
            "parameters": [
                {
                    "id": 124,
                    "display_name": "Toolpath Time",
                    "type": "Double",
                    "value": 3.1512
                }
            ],
            "status": "success"
        },
        {
            "operation_name": "A_K_A7",
            "operation_type": "HoleDrilling",
            "total_params": 1,
            "parameters": [
                {
                    "id": 124,
                    "display_name": "Toolpath Time",
                    "type": "Double",
                    "value": 0.908076
                }
            ],
            "status": "success"
        },
        {
            "operation_name": "A_L_A8",
            "operation_type": "HoleDrilling",
            "total_params": 1,
            "parameters": [
                {
                    "id": 124,
                    "display_name": "Toolpath Time",
                    "type": "Double",
                    "value": 3.71133
                }
            ],
            "status": "success"
        },
        {
            "operation_name": "A_M_A10.5",
            "operation_type": "HoleDrilling",
            "total_params": 1,
            "parameters": [
                {
                    "id": 124,
                    "display_name": "Toolpath Time",
                    "type": "Double",
                    "value": 0.951826
                }
            ],
            "status": "success"
        },
        {
            "operation_name": "B_ZXZ",
            "operation_type": "HoleDrilling",
            "total_params": 1,
            "parameters": [
                {
                    "id": 124,
                    "display_name": "Toolpath Time",
                    "type": "Double",
                    "value": 0.641452
                }
            ],
            "status": "success"
        },
        {
            "operation_name": "B_M1_A13.5",
            "operation_type": "HoleDrilling",
            "total_params": 1,
            "parameters": [
                {
                    "id": 124,
                    "display_name": "Toolpath Time",
                    "type": "Double",
                    "value": 5.97118
                }
            ],
            "status": "success"
        },
        {
            "operation_name": "B_X_M1_D10",
            "operation_type": "CylinderMilling",
            "total_params": 1,
            "parameters": [
                {
                    "id": 124,
                    "display_name": "Toolpath Time",
                    "type": "Double",
                    "value": 5.4223
                }
            ],
            "status": "success"
        },
        {
            "operation_name": "开粗_160_行腔_SIMPLE_50R0.8",
            "operation_type": "CavityMilling",
            "total_params": 1,
            "parameters": [
                {
                    "id": 124,
                    "display_name": "Toolpath Time",
                    "type": "Double",
                    "value": 178.325
                }
            ],
            "status": "success"
        },
        {
            "operation_name": "开粗_160_行腔_SIMPLE_D8",
            "operation_type": "CavityMilling",
            "total_params": 1,
            "parameters": [
                {
                    "id": 124,
                    "display_name": "Toolpath Time",
                    "type": "Double",
                    "value": 516.468
                }
            ],
            "status": "success"
        },
        {
            "operation_name": "开粗_160_行腔_SIMPLE_D4",
            "operation_type": "CavityMilling",
            "total_params": 1,
            "parameters": [
                {
                    "id": 124,
                    "display_name": "Toolpath Time",
                    "type": "Double",
                    "value": 269.855
                }
            ],
            "status": "success"
        }
    ]
}
